fstream/__init__.py
fstream/protocol/__init__.py
fstream/protocol/base.py
fstream/protocol/buffered.py
fstream/protocol/chunked.py
fstream-0.0.6.dist-info/LICENSE
fstream-0.0.6.dist-info/METADATA
fstream-0.0.6.dist-info/WHEEL
fstream-0.0.6.dist-info/top_level.txt
fstream-0.0.6.dist-info/RECORD
